a_pandas_ex_columns_and_index/LICENSE
a_pandas_ex_columns_and_index/README.MD
a_pandas_ex_columns_and_index/__init__.py
a_pandas_ex_columns_and_index/requirements.txt
a_pandas_ex_columns_and_index/thirdparty.json
a_pandas_ex_columns_and_index-0.13.dist-info/LICENSE.rst
a_pandas_ex_columns_and_index-0.13.dist-info/METADATA
a_pandas_ex_columns_and_index-0.13.dist-info/WHEEL
a_pandas_ex_columns_and_index-0.13.dist-info/top_level.txt
a_pandas_ex_columns_and_index-0.13.dist-info/RECORD
